Topsis/__init__.py
Topsis/__main__.py
Topsis_Garima_102017070-1.0.2.dist-info/LICENSE
Topsis_Garima_102017070-1.0.2.dist-info/METADATA
Topsis_Garima_102017070-1.0.2.dist-info/WHEEL
Topsis_Garima_102017070-1.0.2.dist-info/entry_points.txt
Topsis_Garima_102017070-1.0.2.dist-info/top_level.txt
Topsis_Garima_102017070-1.0.2.dist-info/RECORD
