Metadata-Version: 2.1
Name: Topsis-Garima-102017070
Version: 1.0.2
Summary: topsis package for MCDM problems
Home-page: https://github.com/garimachandna/Topsis-Garima-102017070
Author: Garima Chandna
Author-email: gchandna_be20@thapar.edu
License: MIT
Classifier: License :: OSI Approved :: MIT License
Classifier: Programming Language :: Python :: 3.6
Classifier: Programming Language :: Python :: 3.7
Classifier: Programming Language :: Python :: 3.8
Classifier: Programming Language :: Python :: 3.9
Classifier: Programming Language :: Python :: 3.10
License-File: LICENSE
